{
  "family": "Trade",
  "action": "Reply",
  "expected": "SAIC/gL+/v7/ZAL/",
  "properties": [
    {
      "type": "[]protocol/net/server::TradeItemData",
      "name": "trade_data",
      "children": [
        {
          "type": "protocol/net/server::TradeItemData",
          "children": [
            {
              "type": "int",
              "name": "player_id",
              "value": 324
            },
            {
              "type": "[]protocol/net::Item",
              "name": "items",
              "children": [
                {
                  "type": "protocol/net::Item",
                  "children": [
                    {
                      "type": "int",
                      "name": "id",
                      "value": 1
                    },
                    {
                      "type": "int",
                      "name": "amount",
                      "value": 1
                    }
                  ]
                }
              ]
            }
          ]
        },
        {
          "type": "protocol/net/server::TradeItemData",
          "children": [
            {
              "type": "int",
              "name": "player_id",
              "value": 352
            },
            {
              "type": "[]protocol/net::Item",
              "name": "items"
            }
          ]
        }
      ]
    }
  ]
}